docsig/__init__.py
docsig/__main__.py
docsig/_config.py
docsig/_core.py
docsig/_decorators.py
docsig/_directives.py
docsig/_files.py
docsig/_hooks.py
docsig/_main.py
docsig/_module.py
docsig/_report.py
docsig/_stub.py
docsig/_utils.py
docsig/_version.py
docsig/messages.py
docsig/plugin.py
docsig/py.typed
docsig-0.77.0.dist-info/METADATA
docsig-0.77.0.dist-info/WHEEL
docsig-0.77.0.dist-info/entry_points.txt
docsig-0.77.0.dist-info/licenses/LICENSE
docsig-0.77.0.dist-info/RECORD
