Metadata-Version: 2.4
Name: docsig
Version: 0.77.0
Summary: Check signature params for proper documentation
License: MIT
License-File: LICENSE
Keywords: check,docs,docstring,params,signature
Author: jshwi
Author-email: stephen@jshwisolutions.com
Maintainer: jshwi
Maintainer-email: stephen@jshwisolutions.com
Requires-Python: >=3.10,<4.0
Classifier: License :: OSI Approved :: MIT License
Classifier: Programming Language :: Python :: 3
Classifier: Programming Language :: Python :: 3.10
Classifier: Programming Language :: Python :: 3.11
Classifier: Programming Language :: Python :: 3.12
Classifier: Programming Language :: Python :: 3.13
Classifier: Programming Language :: Python :: 3.14
Requires-Dist: Sphinx (>=7,<9)
Requires-Dist: astroid (>=4.0.2,<5.0.0)
Requires-Dist: pathspec (>=0.12.1,<1.1.0)
Requires-Dist: tomli (>=2.0.1,<3.0.0)
Requires-Dist: wcmatch (>=8.5.2,<11.0.0)
Project-URL: Documentation, https://docsig.io/en/latest
Project-URL: Homepage, https://docsig.io
Project-URL: Repository, https://github.com/jshwi/docsig
